Xv6RiscvBookZhongwenbanFix1/README.md
Xv6RiscvBookZhongwenbanFix1/__init__.py
Xv6RiscvBookZhongwenbanFix1/__main__.py
Xv6RiscvBookZhongwenbanFix1/file.epub
Xv6RiscvBookZhongwenbanFix1/index.html
Xv6RiscvBookZhongwenbanFix1/css/__init__.py
Xv6RiscvBookZhongwenbanFix1/css/annotations.css
Xv6RiscvBookZhongwenbanFix1/css/main.css
Xv6RiscvBookZhongwenbanFix1/css/normalize.css
Xv6RiscvBookZhongwenbanFix1/css/popup.css
Xv6RiscvBookZhongwenbanFix1/font/__init__.py
Xv6RiscvBookZhongwenbanFix1/font/fontello.eot
Xv6RiscvBookZhongwenbanFix1/font/fontello.svg
Xv6RiscvBookZhongwenbanFix1/font/fontello.ttf
Xv6RiscvBookZhongwenbanFix1/font/fontello.woff
Xv6RiscvBookZhongwenbanFix1/img/__init__.py
Xv6RiscvBookZhongwenbanFix1/img/annotator-glyph-sprite.png
Xv6RiscvBookZhongwenbanFix1/img/annotator-icon-sprite.png
Xv6RiscvBookZhongwenbanFix1/img/apple-touch-icon.png
Xv6RiscvBookZhongwenbanFix1/img/cancelfullscreen.png
Xv6RiscvBookZhongwenbanFix1/img/close.png
Xv6RiscvBookZhongwenbanFix1/img/fullscreen.png
Xv6RiscvBookZhongwenbanFix1/img/loader.gif
Xv6RiscvBookZhongwenbanFix1/img/menu-icon.png
Xv6RiscvBookZhongwenbanFix1/img/save.png
Xv6RiscvBookZhongwenbanFix1/img/saved.png
Xv6RiscvBookZhongwenbanFix1/img/settings-s.png
Xv6RiscvBookZhongwenbanFix1/img/settings.png
Xv6RiscvBookZhongwenbanFix1/img/star.png
Xv6RiscvBookZhongwenbanFix1/js/__init__.py
Xv6RiscvBookZhongwenbanFix1/js/epub.js
Xv6RiscvBookZhongwenbanFix1/js/epub.min.js
Xv6RiscvBookZhongwenbanFix1/js/epub.min.map
Xv6RiscvBookZhongwenbanFix1/js/hooks.min.js
Xv6RiscvBookZhongwenbanFix1/js/hooks.min.map
Xv6RiscvBookZhongwenbanFix1/js/reader.js
Xv6RiscvBookZhongwenbanFix1/js/reader.js.map
Xv6RiscvBookZhongwenbanFix1/js/reader.min.js
Xv6RiscvBookZhongwenbanFix1/js/reader.min.map
Xv6RiscvBookZhongwenbanFix1/js/hooks/__init__.py
Xv6RiscvBookZhongwenbanFix1/js/hooks/extensions/__init__.py
Xv6RiscvBookZhongwenbanFix1/js/hooks/extensions/highlight.js
Xv6RiscvBookZhongwenbanFix1/js/libs/__init__.py
xv6_riscv_book_zhongwenban_fix1-2025.3.24.1.dist-info/METADATA
xv6_riscv_book_zhongwenban_fix1-2025.3.24.1.dist-info/WHEEL
xv6_riscv_book_zhongwenban_fix1-2025.3.24.1.dist-info/entry_points.txt
xv6_riscv_book_zhongwenban_fix1-2025.3.24.1.dist-info/top_level.txt
xv6_riscv_book_zhongwenban_fix1-2025.3.24.1.dist-info/RECORD
